Metadata-Version: 1.0
Name: sparkling
Version: 1.0.4
Summary: Provide APIs to perform numerical analysis on EOD files based on Spark.
Home-page: https://github.com/yalongwen/sparkling
Author: yalongwen
Author-email: wenyalong@sporttery.cn
License: CSLO
Platform: UNKNOWN
